mlconcepts/ExplanationData.py
mlconcepts/mlconceptscore.pypy39-pp73-win_amd64.pyd
mlconcepts/SODModel.py
mlconcepts/test_models.py
mlconcepts/UODModel.py
mlconcepts/__init__.py
mlconcepts/data/Dataset.py
mlconcepts/data/NumpyLoader.py
mlconcepts/data/PandasLoader.py
mlconcepts/data/PathLoader.py
mlconcepts/data/test_data.py
mlconcepts/data/__init__.py
mlconcepts-0.0.1a5.dist-info/DELVEWHEEL
mlconcepts-0.0.1a5.dist-info/METADATA
mlconcepts-0.0.1a5.dist-info/RECORD
mlconcepts-0.0.1a5.dist-info/top_level.txt
mlconcepts-0.0.1a5.dist-info/WHEEL
mlconcepts.libs/.load-order-mlconcepts-0.0.1a5
mlconcepts.libs/libgcc_s_seh-1-b9987fbbba1b8412a9e4c2a6edf8975d.dll
mlconcepts.libs/libstdc++-6-7e9d270dda53e7d0ee64f5193baaa3b5.dll
mlconcepts.libs/libwinpthread-1-3a3c0bb94b67e97268f712063ec5bbff.dll
