Metadata-Version: 2.1
Name: mlconcepts
Version: 0.0.1a5
Summary: A small library implementing several interpretable machine learning algorithms based on FCA.
Home-page: https://github.com/xeredent/libmlconcepts
Author: Mattia Panettiere
Author-email: mattia.panettiere@gmail.com
License: BSD3
Project-URL: Source, https://github.com/xeredent/libmlconcepts
Project-URL: Tracker, https://github.com/xeredent/libmlconcepts/issues
Keywords: outlier-detection machine-learning formal-concepts-analysis
Platform: any
Classifier: Development Status :: 2 - Pre-Alpha
Classifier: Operating System :: OS Independent
Classifier: Operating System :: POSIX :: Linux
Classifier: Operating System :: MacOS
Classifier: Operating System :: Microsoft :: Windows
Classifier: Intended Audience :: Science/Research
Classifier: Intended Audience :: Developers
Classifier: Programming Language :: C++
Classifier: Programming Language :: Python :: 3 :: Only
Classifier: Programming Language :: Python :: 3
Classifier: Programming Language :: Python :: 3.6
Classifier: Programming Language :: Python :: 3.7
Classifier: Programming Language :: Python :: 3.9
Classifier: Programming Language :: Python :: 3.10
Classifier: Programming Language :: Python :: 3.11
Classifier: Programming Language :: Python :: 3.12
Classifier: License :: OSI Approved :: BSD License
Requires-Python: >=3.6
Provides-Extra: all
Requires-Dist: pytest ; extra == 'all'
Requires-Dist: numpy ; extra == 'all'
Provides-Extra: testing
Requires-Dist: pytest ; extra == 'testing'
Requires-Dist: numpy ; extra == 'testing'
